{"sections":{"breadcrumb":{"type":"breadcrumb","settings":{}},"main":{"type":"main-article","settings":{"show_author":true,"related_heading":"Related articles"}},"shop":{"type":"product-collection","settings":{"heading":"Shop this guide","subtitle":"Hand-picked lighting to bring this look home."}},"newsletter":{"type":"newsletter","settings":{"eyebrow":"Stay in the loop","heading":"Get lighting tips and offers","subtext":"Buying guides, new arrivals and members-only deals, sent occasionally."}}},"order":["breadcrumb","main","shop","newsletter"]}