{
  "sections": {
    "breadcrumb": {
      "type": "breadcrumb",
      "settings": {
        "home_label": "Home",
        "current": "Showroom"
      }
    },
    "hero": {
      "type": "page-hero",
      "settings": {
        "heading": "Our lighting showroom in Doha",
        "subtitle": "See it lit before you buy it. Our showroom has the range on display, and our team can identify a part from a photo or the old bulb in your hand.",
        "bg": "bg-gray"
      }
    },
    "map": {
      "type": "map-embed",
      "settings": {
        "bg": "bg-white",
        "heading": "Find us",
        "subtitle": "Address, hours and directions to the showroom.",
        "eyebrow": "Showroom",
        "showroom_name": "Lighting Souq Showroom",
        "address": "Street address, Doha, Qatar",
        "hours": "Sat to Thu, 9am to 9pm · Fri 4pm to 9pm",
        "phone": "+974 5552 9088",
        "directions_label": "Get directions",
        "directions_link": "/",
        "map_placeholder": "Add a Google Maps embed URL in the theme editor to show the showroom location here.",
        "show_collect": true,
        "collect_title": "Click and Collect",
        "collect_text": "Order online and pick up in store — usually ready the same day."
      }
    },
    "advice": {
      "type": "feature-columns",
      "settings": {
        "heading": "Why visit",
        "subtitle": "",
        "grid_class": "grid-2",
        "bg": "bg-gray"
      },
      "blocks": {
        "a1": { "type": "item", "settings": { "icon": "palette", "title": "Colour temperature is easier to see than to read", "text": "The difference between 2700K, 4000K and 6500K is obvious when it is lit in front of you and almost meaningless on a screen. If you are choosing lighting for a majlis or a whole villa, come and look." } },
        "a2": { "type": "item", "settings": { "icon": "search", "title": "Bring the old part", "text": "A dead bulb, a failed ballast or a photo of the fitting. Our team identifies parts every day, and it is faster in person than over any messaging app." } },
        "a3": { "type": "item", "settings": { "icon": "local_mall", "title": "Collect an online order", "text": "Order on the site and choose collection at checkout. Wait for the confirmation that it is ready before you travel." } },
        "a4": { "type": "item", "settings": { "icon": "engineering", "title": "Talk through a project", "text": "If you are lighting a villa, a cafe or a site, bring the drawings. The specification conversation is the part that saves money later." } }
      },
      "block_order": ["a1", "a2", "a3", "a4"]
    },
    "reviews": {
      "type": "testimonials",
      "settings": {
        "heading": "What showroom visitors say",
        "bg": "bg-white"
      },
      "blocks": {
        "r1": { "type": "review", "settings": { "name": "Ahmed Al-Kuwari", "rating": 5, "text": "Great selection in store and the staff really know lighting. Left with exactly what I needed.", "date": "April 2026" } },
        "r2": { "type": "review", "settings": { "name": "Sara Abdullah", "rating": 5, "text": "Collected my order in store the same day. Quick, friendly and easy.", "date": "March 2026" } },
        "r3": { "type": "review", "settings": { "name": "Mohammed Al-Thani", "rating": 5, "text": "Seeing the lights on before buying made the decision simple. Highly recommend a visit.", "date": "March 2026" } }
      },
      "block_order": ["r1", "r2", "r3"]
    }
  },
  "order": ["breadcrumb", "hero", "map", "advice", "reviews"]
}
